{
  "generated_utc": "2026-01-21T18:05:43.848Z",
  "itemset_hash": "5a9dcd4b61e42f4f",
  "count": 69,
  "items": [
    {
      "title": "Indie Studio Sequel Unveils Upcoming Slate Ahead Of Debut Feature ‘The Musical’s Sundance Premiere",
      "url": "https://deadline.com/2026/01/sequel-unveils-film-slate-the-musical-sundance-1236690274",
      "source": "Deadline",
      "published_utc": "2026-01-21T18:00:00.000Z",
      "effects": {
        "lightsaber": false,
        "glitch": true,
        "reasons": [
          "score≥2.1"
        ],
        "style": "glitch"
      },
      "category": "Labour",
      "region": "World"
    },
    {
      "title": "Rebel Wilson Signs With Range Media Partners",
      "url": "https://deadline.com/2026/01/rebel-wilson-signs-range-media-partners-1236691143",
      "source": "Deadline",
      "published_utc": "2026-01-21T18:00:00.000Z",
      "effects": {
        "lightsaber": false,
        "glitch": false,
        "reasons": []
      },
      "category": "Culture",
      "region": "World"
    },
    {
      "title": "Democrats Gaslight Their Most Loyal Supporters On ICE Funding In 1,059-Page Bill",
      "url": "https://dailycaller.com/2026/01/21/senate-appropriations-committee-ice-detention-beds-funding-chris-murphy-abolish-ice-protests",
      "source": "The Daily Caller",
      "published_utc": "2026-01-21T17:58:46.000Z",
      "effects": {
        "lightsaber": false,
        "glitch": false,
        "reasons": []
      },
      "category": "General",
      "region": "World"
    },
    {
      "title": "Bill Block’s GammaTime Teams With Spikes Studio To Build Vertical Shorts Library",
      "url": "https://deadline.com/2026/01/bill-block-gammatime-spikes-studio-1236691485",
      "source": "Deadline",
      "published_utc": "2026-01-21T18:00:00.000Z",
      "effects": {
        "lightsaber": false,
        "glitch": false,
        "reasons": []
      },
      "category": "Culture",
      "region": "World"
    },
    {
      "title": "Over 4 million temporary resident permits expire in 2025 and 2026: IRCC",
      "url": "https://toronto.citynews.ca/2026/01/21/over-4-million-temporary-resident-permits-expire-in-2025-and-2026-ircc",
      "source": "CityNews Toronto",
      "published_utc": "2026-01-21T17:55:24.000Z",
      "effects": {
        "lightsaber": true,
        "glitch": false,
        "reasons": [
          "score≥2.6"
        ],
        "style": "lightsaber"
      },
      "category": "Local",
      "region": "Canada"
    },
    {
      "title": "C.Y.M. & Abby Sage Announce New EP My Whole World: Hear The Title Track",
      "url": "https://stereogum.com/2486140/c-y-m-abby-sage-announce-new-ep-my-whole-world-hear-the-title-track/music",
      "source": "Stereogum",
      "published_utc": "2026-01-21T17:54:55.000Z",
      "effects": {
        "lightsaber": false,
        "glitch": false,
        "reasons": []
      },
      "category": "Culture",
      "region": "World"
    },
    {
      "title": "Men At Work Denounce Use Of “Down Under” At March For Australia Events",
      "url": "https://stereogum.com/2486141/men-at-work-denounce-use-of-down-under-at-march-for-australia-events/news",
      "source": "Stereogum",
      "published_utc": "2026-01-21T17:54:29.000Z",
      "effects": {
        "lightsaber": false,
        "glitch": false,
        "reasons": []
      },
      "category": "Culture",
      "region": "World"
    },
    {
      "title": "Dem lawmaker demands bank execs be dragged before Congress to testify over Epstein",
      "url": "https://www.rawstory.com/jeffrey-epstein-2674926924",
      "source": "Raw Story",
      "published_utc": "2026-01-21T17:54:11.000Z",
      "effects": {
        "lightsaber": false,
        "glitch": true,
        "reasons": [
          "score≥2.1"
        ],
        "style": "glitch"
      },
      "category": "Labour",
      "region": "World"
    },
    {
      "title": "Footwear Inspirations to Make This the Best Winter Your Feet Have Ever Had",
      "url": "https://www.highsnobiety.com/p/cozy-winter-footwear-buy-online",
      "source": "Highsnobiety",
      "published_utc": "2026-01-21T17:53:04.000Z",
      "effects": {
        "lightsaber": false,
        "glitch": false,
        "reasons": []
      },
      "category": "Culture",
      "region": "World"
    },
    {
      "title": "Is this the End of the Pax Americana? Niall Ferguson Is Live from Davos.",
      "url": "https://www.thefp.com/p/is-this-the-end-of-the-pax-americana",
      "source": "The Free Press",
      "published_utc": "2026-01-21T17:51:32.000Z",
      "effects": {
        "lightsaber": false,
        "glitch": false,
        "reasons": []
      },
      "category": "General",
      "region": "World"
    },
    {
      "title": "Getz: White Sox Expect To Be “Very Active” Following Robert Trade",
      "url": "https://www.mlbtraderumors.com/2026/01/white-sox-rumors-very-active-free-agency-after-luis-robert-trade.html",
      "source": "MLB Trade Rumors",
      "published_utc": "2026-01-21T17:50:57.000Z",
      "effects": {
        "lightsaber": true,
        "glitch": false,
        "reasons": [
          "score≥2.6"
        ],
        "style": "lightsaber"
      },
      "category": "Sports",
      "region": "Canada"
    },
    {
      "title": "James Comer Says ‘Nobody on Our Side Is Defending Pam Bondi’ as Democrat Pushes for Her to Be Held in Contempt Over Epstein Files",
      "url": "https://www.mediaite.com/media/tv/james-comer-says-nobody-on-our-side-is-defending-pam-bondi-as-democrat-pushes-for-her-to-be-held-in-contempt-over-epstein-files",
      "source": "Mediaite",
      "published_utc": "2026-01-21T17:49:33.000Z",
      "effects": {
        "lightsaber": false,
        "glitch": false,
        "reasons": []
      },
      "category": "General",
      "region": "World"
    },
    {
      "title": "Seven more countries agree to join Trump's Board of Peace",
      "url": "https://www.bbc.com/news/articles/cn8jek4vv8ko?at_campaign=rss&at_medium=RSS",
      "source": "BBC News",
      "published_utc": "2026-01-21T17:49:01.000Z",
      "effects": {
        "lightsaber": false,
        "glitch": false,
        "reasons": []
      },
      "category": "General",
      "region": "World"
    },
    {
      "title": "Coheed and Cambria Drummer Plays Black Sabbath Classic as He Hears It for the First Time: Watch",
      "url": "https://consequence.net/2026/01/drumeo-coheed-and-cambria-josh-eppard-black-sabbath",
      "source": "Consequence",
      "published_utc": "2026-01-21T17:48:47.000Z",
      "effects": {
        "lightsaber": false,
        "glitch": false,
        "reasons": []
      },
      "category": "Culture",
      "region": "World"
    },
    {
      "title": "GOP lawmakers called 'pathetic' for Kennedy Center Greenland stunt: 'Remember their names'",
      "url": "https://www.rawstory.com/greenland-cake-republicans",
      "source": "Raw Story",
      "published_utc": "2026-01-21T17:48:37.000Z",
      "effects": {
        "lightsaber": false,
        "glitch": true,
        "reasons": [
          "score≥2.1"
        ],
        "style": "glitch"
      },
      "category": "Labour",
      "region": "World"
    },
    {
      "title": "Oshawa man facing charges after armed robbery at cannabis dispensary",
      "url": "https://toronto.citynews.ca/2026/01/21/oshawa-man-facing-charges-after-armed-robbery-at-cannabis-dispensary",
      "source": "CityNews Toronto",
      "published_utc": "2026-01-21T17:47:43.000Z",
      "effects": {
        "lightsaber": true,
        "glitch": false,
        "reasons": [
          "score≥2.6"
        ],
        "style": "lightsaber"
      },
      "category": "Local",
      "region": "Canada"
    },
    {
      "title": "MARK BRANSCOMBE RELEASES SOLO ALBUM, FIELD RECORDINGS (Interview)",
      "url": "https://canadianbeats.ca/2026/01/21/mark-branscombe-releases-solo-album-field-recordings-interview",
      "source": "Canadian Beats Media",
      "published_utc": "2026-01-21T17:46:36.000Z",
      "effects": {
        "lightsaber": false,
        "glitch": true,
        "reasons": [
          "score≥2.1"
        ],
        "style": "glitch"
      },
      "category": "Culture",
      "region": "Canada"
    },
    {
      "title": "BRIT Awards 2026: here are all the nominees",
      "url": "https://www.nme.com/news/music/brit-awards-2026-nominees-full-list-3924663",
      "source": "NME",
      "published_utc": "2026-01-21T17:45:17.000Z",
      "effects": {
        "lightsaber": false,
        "glitch": false,
        "reasons": []
      },
      "category": "Culture",
      "region": "World"
    },
    {
      "title": "The Perversity of Citing The Black Codes To Defend Gun-Control Laws",
      "url": "https://reason.com/volokh/2026/01/21/the-perversity-of-citing-the-black-codes-to-defend-gun-control-laws",
      "source": "Reason.com",
      "published_utc": "2026-01-21T17:44:43.000Z",
      "effects": {
        "lightsaber": false,
        "glitch": false,
        "reasons": []
      },
      "category": "General",
      "region": "World"
    },
    {
      "title": "Heckler Who Booed Howard Lutnick During Davos Event Revealed to Be Al Gore",
      "url": "https://www.mediaite.com/media/news/heckler-who-booed-howard-lutnick-during-davos-event-revealed-to-be-al-gore",
      "source": "Mediaite",
      "published_utc": "2026-01-21T17:43:22.000Z",
      "effects": {
        "lightsaber": false,
        "glitch": false,
        "reasons": []
      },
      "category": "General",
      "region": "World"
    },
    {
      "title": "A Full Timeline Of Blake Lively & Justin Baldoni’s ‘It Ends With Us’ Feud In Court, Online & In The Media",
      "url": "https://deadline.com/feature/blake-lively-justin-baldoni-feud-timeline-1236279854",
      "source": "Deadline",
      "published_utc": "2026-01-21T17:43:13.000Z",
      "effects": {
        "lightsaber": false,
        "glitch": false,
        "reasons": []
      },
      "category": "Culture",
      "region": "World"
    },
    {
      "title": "In Sundance Push, TikTok Rolls Out New Entertainment Ad Offerings",
      "url": "https://deadline.com/2026/01/sundance-tiktok-entertainment-advertising-1236691539",
      "source": "Deadline",
      "published_utc": "2026-01-21T17:43:03.000Z",
      "effects": {
        "lightsaber": false,
        "glitch": false,
        "reasons": []
      },
      "category": "Culture",
      "region": "World"
    },
    {
      "title": "Toronto man accused of posing as pilot to get hundreds of free flights arrested",
      "url": "https://globalnews.ca/news/11622447/man-pose-pilot-free-flights-canadian-arrested",
      "source": ": Toronto",
      "published_utc": "2026-01-21T17:42:52.000Z",
      "effects": {
        "lightsaber": true,
        "glitch": false,
        "reasons": [
          "score≥2.6"
        ],
        "style": "lightsaber"
      },
      "category": "Local",
      "region": "Canada"
    },
    {
      "title": "Inside ‘Star Search’: Netflix Takes On Broadcast With Its First Live Competition Series",
      "url": "https://deadline.com/2026/01/inside-star-search-netflix-first-live-competition-series-1236691262",
      "source": "Deadline",
      "published_utc": "2026-01-21T17:42:29.000Z",
      "effects": {
        "lightsaber": false,
        "glitch": false,
        "reasons": []
      },
      "category": "Culture",
      "region": "World"
    },
    {
      "title": "AGC Studios Promotes Zach Garrett To Head Of Film",
      "url": "https://deadline.com/2026/01/agc-studios-zach-garrett-head-of-film-1236691727",
      "source": "Deadline",
      "published_utc": "2026-01-21T17:42:03.000Z",
      "effects": {
        "lightsaber": false,
        "glitch": true,
        "reasons": [
          "score≥2.1"
        ],
        "style": "glitch"
      },
      "category": "Labour",
      "region": "World"
    },
    {
      "title": "NHL’s American players among the most right-leaning in pro sports: Report",
      "url": "https://toronto.citynews.ca/2026/01/21/nhls-american-players-among-the-most-right-leaning-in-pro-sports-report",
      "source": "CityNews Toronto",
      "published_utc": "2026-01-21T17:39:43.000Z",
      "effects": {
        "lightsaber": true,
        "glitch": false,
        "reasons": [
          "score≥2.6"
        ],
        "style": "lightsaber"
      },
      "category": "Labour",
      "region": "Canada"
    },
    {
      "title": "Justice Sotomayor comes out swinging in 'irregular' Trump case: 'I'm hard pressed'",
      "url": "https://www.rawstory.com/sotomayor-trump-cook-2674921583",
      "source": "Raw Story",
      "published_utc": "2026-01-21T17:39:08.000Z",
      "effects": {
        "lightsaber": false,
        "glitch": true,
        "reasons": [
          "score≥2.1"
        ],
        "style": "glitch"
      },
      "category": "Labour",
      "region": "World"
    },
    {
      "title": "Puff, Puff... Pass",
      "url": "https://www.highsnobiety.com/p/puff-puff-pass",
      "source": "Highsnobiety",
      "published_utc": "2026-01-21T17:38:48.000Z",
      "effects": {
        "lightsaber": false,
        "glitch": true,
        "reasons": [
          "score≥2.1"
        ],
        "style": "glitch"
      },
      "category": "Labour",
      "region": "World"
    },
    {
      "title": "OPP stop tire‑less truck rolling down QEW, Brampton man charged",
      "url": "https://toronto.citynews.ca/2026/01/21/opp-man-charged-truck-no-tires-brampton-qew",
      "source": "CityNews Toronto",
      "published_utc": "2026-01-21T17:37:54.000Z",
      "effects": {
        "lightsaber": true,
        "glitch": false,
        "reasons": [
          "score≥2.6"
        ],
        "style": "lightsaber"
      },
      "category": "Local",
      "region": "Canada"
    },
    {
      "title": "U18 B.C. hockey player didn’t let a scorpion sting cost his team the final",
      "url": "https://globalnews.ca/news/11621906/u18-bc-hockey-player-scorpion-sting-win-final",
      "source": "globalnews.ca",
      "published_utc": "2026-01-21T17:36:56.000Z",
      "effects": {
        "lightsaber": true,
        "glitch": false,
        "reasons": [
          "score≥2.6"
        ],
        "style": "lightsaber"
      },
      "category": "General",
      "region": "Canada"
    },
    {
      "title": "Ashton Kutcher Addresses Hygiene Habits After Nasty Rumors Went Viral Years Ago",
      "url": "https://dailycaller.com/2026/01/21/ashton-kutcher-hygiene-habits-showers-mila-kunis-clean-viral-rumors",
      "source": "The Daily Caller",
      "published_utc": "2026-01-21T17:36:04.000Z",
      "effects": {
        "lightsaber": false,
        "glitch": false,
        "reasons": []
      },
      "category": "General",
      "region": "World"
    },
    {
      "title": "STEPHEN MOORE: This Is No Way To Gimme Shelter",
      "url": "https://dailycaller.com/2026/01/21/opinion-this-is-no-way-to-gimme-shelter-stephen-moore",
      "source": "The Daily Caller",
      "published_utc": "2026-01-21T17:35:45.000Z",
      "effects": {
        "lightsaber": false,
        "glitch": false,
        "reasons": []
      },
      "category": "General",
      "region": "World"
    },
    {
      "title": "Rand Paul Turns Against Section 230, Citing YouTube Video Accusing Him of Taking Money From Maduro",
      "url": "https://reason.com/2026/01/21/rand-paul-turns-against-section-230-citing-youtube-video-accusing-him-of-taking-money-from-maduro",
      "source": "Reason.com",
      "published_utc": "2026-01-21T17:35:12.000Z",
      "effects": {
        "lightsaber": false,
        "glitch": false,
        "reasons": []
      },
      "category": "General",
      "region": "World"
    },
    {
      "title": "Sunny Hostin Whines About Trump Holding Up Photos Of Illegal Alien Criminals Because They Are Black And Brown",
      "url": "https://dailycaller.com/2026/01/21/the-view-sunny-hostin-trump-illegal-alien-criminals-mugshots",
      "source": "The Daily Caller",
      "published_utc": "2026-01-21T17:32:48.000Z",
      "effects": {
        "lightsaber": false,
        "glitch": false,
        "reasons": []
      },
      "category": "General",
      "region": "World"
    },
    {
      "title": "Republican candidate made fortune from company helping Nicolas Maduro spy on Venezuelans",
      "url": "https://www.rawstory.com/republican-candidate-made-fortune-from-company-helping-nicolas-maduro-spy-on-venezuelans",
      "source": "Raw Story",
      "published_utc": "2026-01-21T17:31:06.000Z",
      "effects": {
        "lightsaber": false,
        "glitch": true,
        "reasons": [
          "score≥2.1"
        ],
        "style": "glitch"
      },
      "category": "Labour",
      "region": "World"
    },
    {
      "title": "Former Turnstile Guitarist Brady Ebert Launches New Band The S.E.T., Shares First Song",
      "url": "https://stereogum.com/2486125/former-turnstile-guitarist-brady-ebert-launches-new-band-the-s-e-t-shares-first-song/music",
      "source": "Stereogum",
      "published_utc": "2026-01-21T17:30:51.000Z",
      "effects": {
        "lightsaber": false,
        "glitch": false,
        "reasons": []
      },
      "category": "Culture",
      "region": "World"
    },
    {
      "title": "‘Just Pure Fiction’: CNN Fact Checker Shreds Trump’s ‘Barrage of False Claims’ in Davos Speech",
      "url": "https://www.mediaite.com/politics/trump/just-pure-fiction-cnn-fact-checker-shreds-trumps-barrage-of-false-claims-in-davos-speech",
      "source": "Mediaite",
      "published_utc": "2026-01-21T17:30:26.000Z",
      "effects": {
        "lightsaber": false,
        "glitch": false,
        "reasons": []
      },
      "category": "General",
      "region": "World"
    },
    {
      "title": "Chevron-Led Tengiz Oilfield Offline for Another Week After Fire",
      "url": "https://oilprice.com/Latest-Energy-News/World-News/Chevron-Led-Tengiz-Oilfield-Offline-for-Another-Week-After-Fire.html",
      "source": "Oilprice.com",
      "published_utc": "2026-01-21T17:30:00.000Z",
      "effects": {
        "lightsaber": true,
        "glitch": false,
        "reasons": [
          "score≥2.6"
        ],
        "style": "lightsaber"
      },
      "category": "Energy",
      "region": "Canada"
    },
    {
      "title": "Ella Stiller Joins Mike Colter In CBS Legal Drama ‘Cupertino’ From Robert & Michelle King",
      "url": "https://deadline.com/2026/01/ella-stiller-joins-cupertino-cbs-1236691418",
      "source": "Deadline",
      "published_utc": "2026-01-21T17:30:00.000Z",
      "effects": {
        "lightsaber": false,
        "glitch": true,
        "reasons": [
          "score≥2.1"
        ],
        "style": "glitch"
      },
      "category": "Labour",
      "region": "World"
    },
    {
      "title": "‘Therapuss With Jake Shane’ & ‘48 Hours’ Podcast Joining Netflix As Streamer Continues Audio Push",
      "url": "https://deadline.com/2026/01/therapuss-with-jake-shane-48-hours-podcast-netflix-1236690355",
      "source": "Deadline",
      "published_utc": "2026-01-21T17:30:00.000Z",
      "effects": {
        "lightsaber": false,
        "glitch": false,
        "reasons": []
      },
      "category": "Culture",
      "region": "World"
    },
    {
      "title": "Super Saliha",
      "url": "https://www.aljazeera.com/video/al-jazeera-world/2026/1/21/super-saliha?traffic_source=rss",
      "source": "Al Jazeera – Breaking News, World News and Video from Al Jazeera",
      "published_utc": "2026-01-21T17:30:00.000Z",
      "effects": {
        "lightsaber": false,
        "glitch": false,
        "reasons": []
      },
      "category": "General",
      "region": "World"
    },
    {
      "title": "Tsuut’ina Nation police charge woman with 2nd-degree murder",
      "url": "https://globalnews.ca/news/11622679/tsuutina-nation-police-second-degree-murder-charge-amanda-crane",
      "source": "globalnews.ca",
      "published_utc": "2026-01-21T17:29:44.000Z",
      "effects": {
        "lightsaber": true,
        "glitch": false,
        "reasons": [
          "score≥2.6"
        ],
        "style": "breaker"
      },
      "category": "General",
      "region": "Canada"
    },
    {
      "title": "New condo sales in Greater Toronto Hamilton Area plunge to lowest level since 1991",
      "url": "https://www.canadianmortgagetrends.com/2026/01/new-condo-sales-in-greater-toronto-hamilton-area-plunge-to-lowest-level-since-1991",
      "source": "CMT News",
      "published_utc": "2026-01-21T17:27:58.000Z",
      "effects": {
        "lightsaber": true,
        "glitch": false,
        "reasons": [
          "score≥2.6"
        ],
        "style": "lightsaber"
      },
      "category": "Real Estate",
      "region": "Canada"
    },
    {
      "title": "Israeli strike in Gaza kills three journalists, first responders say",
      "url": "https://www.bbc.com/news/articles/c98pnzp50nqo?at_campaign=rss&at_medium=RSS",
      "source": "BBC News",
      "published_utc": "2026-01-21T17:27:58.000Z",
      "effects": {
        "lightsaber": false,
        "glitch": true,
        "reasons": [
          "score≥2.1"
        ],
        "style": "glitch"
      },
      "category": "Labour",
      "region": "World"
    },
    {
      "title": "Trump rules out using force to take over Greenland, calls for negotiations",
      "url": "https://www.aljazeera.com/news/2026/1/21/trump-rules-out-using-force-to-take-over-greenland-calls-for-negotiations?traffic_source=rss",
      "source": "Al Jazeera – Breaking News, World News and Video from Al Jazeera",
      "published_utc": "2026-01-21T17:27:12.000Z",
      "effects": {
        "lightsaber": false,
        "glitch": false,
        "reasons": []
      },
      "category": "General",
      "region": "World"
    },
    {
      "title": "Phil Collins: “Everything That Could Go Wrong With Me Did Go Wrong With Me”",
      "url": "https://consequence.net/2026/01/phil-collins-health-update-2026",
      "source": "Consequence",
      "published_utc": "2026-01-21T17:27:03.000Z",
      "effects": {
        "lightsaber": false,
        "glitch": true,
        "reasons": [
          "score≥2.1"
        ],
        "style": "glitch"
      },
      "category": "Culture",
      "region": "Canada"
    },
    {
      "title": "Leavitt pummeled for 'lying' about Trump's latest Greenland misstatement: 'She's pathetic'",
      "url": "https://www.rawstory.com/leavitt-trump-iceland",
      "source": "Raw Story",
      "published_utc": "2026-01-21T17:25:14.000Z",
      "effects": {
        "lightsaber": false,
        "glitch": false,
        "reasons": []
      },
      "category": "Labour",
      "region": "World"
    },
    {
      "title": "US to transfer Islamic State prisoners from Syria to Iraq",
      "url": "https://www.bbc.com/news/articles/cx20pwqkgp9o?at_campaign=rss&at_medium=RSS",
      "source": "BBC News",
      "published_utc": "2026-01-21T17:24:56.000Z",
      "effects": {
        "lightsaber": false,
        "glitch": false,
        "reasons": []
      },
      "category": "General",
      "region": "World"
    },
    {
      "title": "Teamworks, the “operating system for sports,” buys hockey analytics platform Sportlogiq",
      "url": "https://betakit.com/teamworks-the-operating-system-for-sports-buys-hockey-analytics-platform-sportlogiq",
      "source": "BetaKit",
      "published_utc": "2026-01-21T17:24:47.000Z",
      "effects": {
        "lightsaber": true,
        "glitch": false,
        "reasons": [
          "score≥2.6"
        ],
        "style": "lightsaber"
      },
      "category": "Labour",
      "region": "Canada"
    },
    {
      "title": "Gregory Uhlmann Announces New Album Extra Stars: Hear “Lucia” (Feat. Alabaster DePlume)",
      "url": "https://stereogum.com/2486124/gregory-uhlmann-announces-new-album-extra-stars-hear-lucia-feat-alabaster-deplume/music",
      "source": "Stereogum",
      "published_utc": "2026-01-21T17:23:58.000Z",
      "effects": {
        "lightsaber": false,
        "glitch": false,
        "reasons": []
      },
      "category": "Culture",
      "region": "World"
    },
    {
      "title": "Insurers Bragged About Being Woke While Bilking Taxpayers",
      "url": "https://dailycaller.com/2026/01/21/insurers-bragged-about-being-woke-while-bilking-taxpayers",
      "source": "The Daily Caller",
      "published_utc": "2026-01-21T17:23:44.000Z",
      "effects": {
        "lightsaber": false,
        "glitch": false,
        "reasons": []
      },
      "category": "General",
      "region": "World"
    },
    {
      "title": "Trump and Zelenskyy to meet as harsh weather could impact Russian invasion",
      "url": "https://globalnews.ca/news/11622668/ukraine-russia-invasion-trump-zelenskyy-meeting",
      "source": "globalnews.ca",
      "published_utc": "2026-01-21T17:23:41.000Z",
      "effects": {
        "lightsaber": true,
        "glitch": false,
        "reasons": [
          "score≥2.6"
        ],
        "style": "lightsaber"
      },
      "category": "General",
      "region": "Canada"
    },
    {
      "title": "Acne Studios FW26: Between Aristocratic Elegance & Subcultural Style",
      "url": "https://hypebeast.com/2026/1/acne-studios-fw26-between-aristocratic-elegance-subcultural-style",
      "source": "Hypebeast",
      "published_utc": "2026-01-21T17:23:21.000Z",
      "effects": {
        "lightsaber": true,
        "glitch": false,
        "reasons": [
          "score≥2.6"
        ],
        "style": "lightsaber"
      },
      "category": "Labour",
      "region": "Canada"
    },
    {
      "title": "CNN’s Kaitlan Collins and Gavin Newsom Call Out Trump Gaffes From ‘Jaw-Dropping’ Davos Speech",
      "url": "https://www.mediaite.com/media/news/cnns-kaitlan-collins-and-gavin-newsom-call-out-trump-gaffes-from-jaw-dropping-davos-speech",
      "source": "Mediaite",
      "published_utc": "2026-01-21T17:20:19.000Z",
      "effects": {
        "lightsaber": false,
        "glitch": false,
        "reasons": []
      },
      "category": "General",
      "region": "World"
    },
    {
      "title": "‘Percy Jackson And The Olympians’ Season 3 Set For Later This Year; First Look Teases Percy & Annabeth’s Anticipated Dance Scene",
      "url": "https://deadline.com/2026/01/percy-jackson-and-the-olympians-season-3-release-date-teaser-1236691636",
      "source": "Deadline",
      "published_utc": "2026-01-21T17:19:07.000Z",
      "effects": {
        "lightsaber": false,
        "glitch": false,
        "reasons": []
      },
      "category": "Culture",
      "region": "World"
    },
    {
      "title": "Lightning Bolt and OOIOO Join Forces for Split LP",
      "url": "https://pitchfork.com/news/lightning-bolt-and-ooioo-join-forces-for-split-lp",
      "source": "RSS: News",
      "published_utc": "2026-01-21T17:16:28.000Z",
      "effects": {
        "lightsaber": false,
        "glitch": false,
        "reasons": []
      },
      "category": "Culture",
      "region": "World"
    },
    {
      "title": "Sylvester Stallone’s Balboa Prods. Re-Ups First-Look Film & Television Deal With Amazon MGM Studios",
      "url": "https://deadline.com/2026/01/sylvester-stallone-balboa-prods-new-amazon-mgm-studios-deal-1236691007",
      "source": "Deadline",
      "published_utc": "2026-01-21T17:15:00.000Z",
      "effects": {
        "lightsaber": false,
        "glitch": false,
        "reasons": []
      },
      "category": "Labour",
      "region": "World"
    },
    {
      "title": "Scott Bessent Slams Gavin Newsom for Being a Cross Between ‘American Psycho’ and a Ken Doll",
      "url": "https://www.mediaite.com/politics/scott-bessent-slams-gavin-newsom-for-being-a-cross-between-american-psycho-and-a-ken-doll",
      "source": "Mediaite",
      "published_utc": "2026-01-21T17:14:23.000Z",
      "effects": {
        "lightsaber": false,
        "glitch": false,
        "reasons": []
      },
      "category": "General",
      "region": "World"
    },
    {
      "title": "Witch Fever left “broke” after playing two months in arenas",
      "url": "https://www.nme.com/news/music/witch-fever-left-broke-after-playing-two-months-in-arenas-3924674",
      "source": "NME",
      "published_utc": "2026-01-21T17:13:26.000Z",
      "effects": {
        "lightsaber": false,
        "glitch": false,
        "reasons": []
      },
      "category": "Culture",
      "region": "World"
    },
    {
      "title": "Mute Clothes at Full Blast",
      "url": "https://www.highsnobiety.com/p/latest-products",
      "source": "Highsnobiety",
      "published_utc": "2026-01-21T17:12:28.000Z",
      "effects": {
        "lightsaber": false,
        "glitch": false,
        "reasons": []
      },
      "category": "Culture",
      "region": "World"
    },
    {
      "title": "Montreal grocery stores and restaurants may soon be required to donate unsold food to food banks",
      "url": "https://cultmtl.com/2026/01/montreal-grocery-stores-and-restaurants-may-soon-be-required-to-donate-unsold-food-to-food-banks",
      "source": "Cult MTL",
      "published_utc": "2026-01-21T17:09:52.000Z",
      "effects": {
        "lightsaber": true,
        "glitch": false,
        "reasons": [
          "score≥2.6"
        ],
        "style": "lightsaber"
      },
      "category": "Culture",
      "region": "Canada"
    },
    {
      "title": "Jack White Mocks Trump’s Anniversary Press Conference: “Me Do Accomplishments!”",
      "url": "https://consequence.net/2026/01/jack-white-trump-me-do-accomplishments",
      "source": "Consequence",
      "published_utc": "2026-01-21T17:09:01.000Z",
      "effects": {
        "lightsaber": false,
        "glitch": false,
        "reasons": []
      },
      "category": "Culture",
      "region": "World"
    },
    {
      "title": "Appeasement never works — it's time for Europe to deploy its ultimate weapon",
      "url": "https://www.rawstory.com/appeasement-never-works-it-s-time-for-europe-to-wield-its-ultimate-weapon",
      "source": "Raw Story",
      "published_utc": "2026-01-21T17:04:09.000Z",
      "effects": {
        "lightsaber": false,
        "glitch": false,
        "reasons": []
      },
      "category": "General",
      "region": "World"
    },
    {
      "title": "Timothy Busfield Released Without Bail Amid Child Sex Case",
      "url": "https://dailycaller.com/2026/01/21/west-wing-timothy-busfield-win-court-child-sex-abuse-case-bail",
      "source": "The Daily Caller",
      "published_utc": "2026-01-21T17:01:50.000Z",
      "effects": {
        "lightsaber": false,
        "glitch": false,
        "reasons": []
      },
      "category": "General",
      "region": "World"
    },
    {
      "title": "New on Netflix Canada: February 2026",
      "url": "https://mobilesyrup.com/2026/01/21/new-netflix-canada-february-2026",
      "source": "MobileSyrup",
      "published_utc": "2026-01-21T17:01:22.000Z",
      "effects": {
        "lightsaber": true,
        "glitch": false,
        "reasons": [
          "score≥2.6"
        ],
        "style": "lightsaber"
      },
      "category": "Tech",
      "region": "Canada"
    },
    {
      "title": "Gen Z Progressive Says She Was Too Sleepy To Make It To Key Campaign Event",
      "url": "https://dailycaller.com/2026/01/21/kat-abughazaleh-narcolepsy-indivisible-campaign-event",
      "source": "The Daily Caller",
      "published_utc": "2026-01-21T17:01:00.000Z",
      "effects": {
        "lightsaber": false,
        "glitch": false,
        "reasons": []
      },
      "category": "General",
      "region": "World"
    },
    {
      "title": "The Real Reason Washington Wants Venezuela’s Oil",
      "url": "https://oilprice.com/Energy/Energy-General/The-Real-Reason-Washington-Wants-Venezuelas-Oil.html",
      "source": "Oilprice.com",
      "published_utc": "2026-01-21T17:00:00.000Z",
      "effects": {
        "lightsaber": true,
        "glitch": false,
        "reasons": [
          "score≥2.6"
        ],
        "style": "lightsaber"
      },
      "category": "Energy",
      "region": "Canada"
    },
    {
      "title": "Ang Lee Set For ACE Eddie Awards 2026 Filmmaker Of The Year Honor",
      "url": "https://deadline.com/2026/01/ang-lee-eddie-awards-2026-filmmaker-of-the-year-1236690580",
      "source": "Deadline",
      "published_utc": "2026-01-21T17:00:00.000Z",
      "effects": {
        "lightsaber": false,
        "glitch": false,
        "reasons": []
      },
      "category": "Culture",
      "region": "World"
    },
    {
      "title": "Trump's Greenland gambit backfires as EU suspends work on US trade deal",
      "url": "https://www.rawstory.com/trump-greenland-eu-trade-deal",
      "source": "Raw Story",
      "published_utc": "2026-01-21T16:58:42.000Z",
      "effects": {
        "lightsaber": false,
        "glitch": false,
        "reasons": []
      },
      "category": "General",
      "region": "World"
    }
  ],
  "_debug": {
    "feeds_total": 154,
    "cap_items": 320,
    "collected": 657,
    "dedup_pass1": 650,
    "dedup_final": 320,
    "slow_domains": [],
    "timeouts": [
      "news.communitech.ca",
      "www.cbc.ca"
    ],
    "errors": [
      "alert.weather.gc.ca",
      "feeds.reuters.com"
    ],
    "caps_hit": [
      "cultmtl.com",
      "financialpost.com",
      "globalnews.ca",
      "toronto.citynews.ca"
    ],
    "feed_times_sample": [
      {
        "host": "toronto.citynews.ca",
        "sec": 2.276,
        "kept": 8
      },
      {
        "host": "www.labourstart.org",
        "sec": 1.509,
        "kept": 0
      },
      {
        "host": "globalnews.ca",
        "sec": 0.629,
        "kept": 10
      },
      {
        "host": "www.blogto.com",
        "sec": 0.426,
        "kept": 0
      },
      {
        "host": "www.cp24.com",
        "sec": 0.413,
        "kept": 14
      },
      {
        "host": "www.mlb.com",
        "sec": 0.346,
        "kept": 14
      },
      {
        "host": "www.mlbtraderumors.com",
        "sec": 0.338,
        "kept": 14
      },
      {
        "host": "www.bls.gov",
        "sec": 0.242,
        "kept": 0
      },
      {
        "host": "www.federalreserve.gov",
        "sec": 0.19,
        "kept": 14
      },
      {
        "host": "www.nhl.com",
        "sec": 0.188,
        "kept": 0
      }
    ],
    "elapsed_sec": 328.5,
    "http_timeout_sec": 10,
    "slow_feed_warn_sec": 3.5,
    "global_budget_sec": 210,
    "version": "fetch-v2.7.0-obits-am-bias",
    "weights_loaded": true,
    "weights_keys": [
      "categories",
      "daypart",
      "effects",
      "labour_keywords",
      "markets",
      "public_safety",
      "recency",
      "regional",
      "reorder",
      "salience",
      "sources",
      "sports",
      "timezone"
    ],
    "weights_error": "",
    "weights_path": "config/weights.json5",
    "score_stats": {
      "effects_lightsaber": 0,
      "effects_glitch": 0,
      "ps_fatal_hits": 16,
      "ps_injury_hits": 0,
      "market_btc_hits": 0,
      "market_index_hits": 0,
      "market_nikkei_hits": 0,
      "market_single_hits": 0,
      "agg_penalties": 0,
      "press_penalties": 0,
      "preferred_bonus": 120,
      "substack_tagged": 0,
      "sports_team_hits": 6,
      "sports_player_hits": 2,
      "sports_result_win_hits": 22,
      "sports_result_loss_hits": 1,
      "sports_evening_hits": 0,
      "sports_playoff_hits": 0,
      "sports_focus_team_hits": 3,
      "sports_final_hits": 0,
      "sports_final_score_hits": 0,
      "hype_politics": 0,
      "hype_conflict": 0,
      "hype_markets": 0,
      "hype_jobs": 0,
      "hype_sports": 0,
      "hype_ceasefire": 0,
      "reject_hits": 1,
      "obit_hits": 3,
      "major_figure_hits": 4,
      "business_am_hits": 0
    },
    "sanity_stats": {
      "link_verification_fail": 30,
      "soft_404_drops": 42,
      "max_age_drops": 0,
      "min_age_drops": 8,
      "market_sanity_drops": 6,
      "backfill_steps_used": 0
    },
    "require_exact_count": 69,
    "age_window_hours": 69,
    "min_age_sec": 60,
    "verify_links": true,
    "reject_homepage_redirect": true,
    "block_aggregators": true,
    "fallback": {
      "used": false,
      "feed": null,
      "title": null,
      "feeds_considered": [
        "https://www.reuters.com/world/us/rss",
        "https://www.reuters.com/world/rss",
        "https://www.cbc.ca/cmlink/rss-topstories",
        "https://www.ctvnews.ca/rss/ctvnews-ca-top-stories-public-rss-1.822009",
        "https://globalnews.ca/feed/",
        "https://www.cp24.com"
      ],
      "max_age_hours": 24,
      "min_items": 1
    }
  }
}
